izsdk/File.py
izsdk/Folder.py
izsdk/__init__.py
izsdk/auth.py
izsdk/cache.py
izsdk/config.py
izsdk/connectionPool.py
izsdk/item.py
izsdk/iz_uuid.py
izsdk/manageUser.py
izsdk/organization.py
izsdk/permissions.py
izsdk/request_pb2.py
izsdk/response_pb2.py
izsdk/role.py
izsdk/sdk.py
izsdk/share.py
izsdk/tableUser.py
izsdk/team.py
izsdk/user.py
izsdk-1.0.4.dist-info/licenses/LICENSE
izsdk-1.0.4.dist-info/METADATA
izsdk-1.0.4.dist-info/WHEEL
izsdk-1.0.4.dist-info/top_level.txt
izsdk-1.0.4.dist-info/RECORD
