Metadata-Version: 2.4
Name: izsdk
Version: 1.0.4
Summary: Ysafe SDK for interacting with the Ysafe API
License: MIT
Project-URL: Homepage, https://github.com/Induzio/iz-python
Requires-Python: >=3.8
License-File: LICENSE
Requires-Dist: beautifulsoup4>=4.13.4
Requires-Dist: cachetools>=6.1.0
Requires-Dist: google>=3.0.0
Requires-Dist: iniconfig>=2.1.0
Requires-Dist: packaging>=25.0
Requires-Dist: pluggy>=1.6.0
Requires-Dist: protobuf>=6.31.1
Requires-Dist: Pygments>=2.19.2
Requires-Dist: asyncio>=1.0.0
Requires-Dist: soupsieve>=2.7
Requires-Dist: typing_extensions>=4.14.0
Requires-Dist: websockets>=15.0.1
Dynamic: license-file
